wbdutil/__init__.py
wbdutil/__main__.py
wbdutil/wbdutil.py
wbdutil/commands/__init__.py
wbdutil/commands/download.py
wbdutil/commands/ingest.py
wbdutil/commands/list_osdu.py
wbdutil/commands/parse.py
wbdutil/commands/search.py
wbdutil/commands/update.py
wbdutil/common/__init__.py
wbdutil/common/configuration.py
wbdutil/common/exceptions.py
wbdutil/common/file_loader.py
wbdutil/common/reflection_utilities.py
wbdutil/service/__init__.py
wbdutil/service/property_mapping.py
wbdutil/service/record_mapper.py
wbdutil/service/well_service.py
wbdutil/wrapper/__init__.py
wbdutil/wrapper/environment_var_helper.py
wbdutil/wrapper/json_writer.py
wbdutil/wrapper/osdu_client.py
wbdutil-0.1.1.dist-info/licenses/LICENSE
wbdutil-0.1.1.dist-info/METADATA
wbdutil-0.1.1.dist-info/WHEEL
wbdutil-0.1.1.dist-info/entry_points.txt
wbdutil-0.1.1.dist-info/top_level.txt
wbdutil-0.1.1.dist-info/RECORD
