Metadata-Version: 2.4
Name: wbdutil
Version: 0.1.1
Summary: OSDU Wellbore DDMS Data Loader - command line interface
Author-email: "BP, SLB" <greg.harris1@bp.com>
License-Expression: Apache-2.0
Project-URL: Homepage, https://community.opengroup.org/osdu/platform/data-flow/data-loading/wellbore-ddms-las-loader
Project-URL: issue-tracker, https://community.opengroup.org/osdu/platform/data-flow/data-loading/wellbore-ddms-las-loader/-/issues
Keywords: osdu
Classifier: Environment :: Console
Classifier: Natural Language :: English
Classifier: Programming Language :: Python :: 3.13
Requires-Python: >=3.13
License-File: LICENSE
Requires-Dist: anyio
Requires-Dist: argcomplete
Requires-Dist: certifi
Requires-Dist: charset-normalizer
Requires-Dist: colorama
Requires-Dist: h11
Requires-Dist: httpcore
Requires-Dist: httpx
Requires-Dist: idna
Requires-Dist: jmespath
Requires-Dist: knack
Requires-Dist: lasio
Requires-Dist: numpy
Requires-Dist: pandas
Requires-Dist: pyarrow
Requires-Dist: pygments
Requires-Dist: python-dateutil
Requires-Dist: pytz
Requires-Dist: pyyaml
Requires-Dist: rfc3986[idna2008]
Requires-Dist: six
Requires-Dist: sniffio
Requires-Dist: tabulate
Provides-Extra: dev
Requires-Dist: pip-tools>=7.5.1; extra == "dev"
Requires-Dist: pytest; extra == "dev"
Requires-Dist: pytest-cov; extra == "dev"
Requires-Dist: respx; extra == "dev"
Requires-Dist: pylint; extra == "dev"
Requires-Dist: isort; extra == "dev"
Requires-Dist: flake8; extra == "dev"
Requires-Dist: pytype; extra == "dev"
Dynamic: license-file
